brainfuckmachine/__init__.py
brainfuckmachine/brainfuckmachine.hy
brainfuckmachine/lib_brainfuckmachine.hy
brainfuckmachine-0.1.1.28.dist-info/LICENSE
brainfuckmachine-0.1.1.28.dist-info/METADATA
brainfuckmachine-0.1.1.28.dist-info/WHEEL
brainfuckmachine-0.1.1.28.dist-info/top_level.txt
brainfuckmachine-0.1.1.28.dist-info/RECORD
