Metadata-Version: 2.1
Name: brainfuckmachine
Version: 0.1.1.28
Summary: Simple Brainfuck compiler for python
Home-page: https://bitbucket.org/schrodenkatzen/brainfuckmachine/src/master/
Author: Vlad Havrilov
Author-email: wladgavrilov@gmail.com
License: UNKNOWN
Platform: UNKNOWN
Classifier: Programming Language :: Python :: 3
Classifier: License :: OSI Approved :: MIT License
Classifier: Operating System :: OS Independent
Requires-Dist: hy
